Acumulador/Acumulador.v
module acc(
    input clk, 
    input add, 
    input reset, 
    output reg [3:0] count 
); 
    
    initial count = 0; 

    always @(posedge clk) begin
        if (reset) begin      
            count <= 4'b0;
        end
        else if (add) begin   
            count <= count + 1;
        end
    end

endmodule

Acumulador/Acumulador_tb.v
`timescale 1s / 1ms   // Definimos la unidad en segundos para que sea lento

module acc_TB;

   reg clk;
   reg add;
   reg reset; // Cambiado rst -> reset para coincidir con tu módulo
   wire [3:0] count;

   // Conexión exacta con los puertos de tu módulo 'acc'
   acc uut( 
       .clk(clk), 
       .add(add), 
       .reset(reset), 
       .count(count) 
   );

   // Parámetros para un reloj de 1 segundo (Periodo = 1)
   parameter PERIOD          = 1.0;
   parameter real DUTY_CYCLE = 0.5;
   parameter OFFSET          = 0.1;

   // Generador de Reloj (1 segundo por ciclo)
   initial begin
     #OFFSET;
     forever begin
         clk = 1'b0;
         #(PERIOD * (1 - DUTY_CYCLE)) clk = 1'b1;
         #(PERIOD * DUTY_CYCLE);
     end
   end

   // Lógica de estímulos adaptada
   integer i; // Usamos integer para el bucle
   initial begin 
        // Estado inicial
        reset = 0; add = 0;
        clk = 0;

        // Proceso de Reset
        #0.5 reset = 1;     // Activa reset
        @(posedge clk);     // Espera un flanco de subida
        @(negedge clk);     // Espera un flanco de bajada
        reset = 0;          // Desactiva reset
        
        // Empezar a contar
        @(posedge clk);
        add = 1;

        // Contar durante 10 ciclos (10 segundos)
        for(i=0; i<10; i=i+1) begin
            @(posedge clk);
        end

        add = 0;            // Deja de contar
        #2 $finish;         // Espera 2 segundos más y termina
   end

   // Configuración para GTKWave
   initial begin: TEST_CASE
     $dumpfile("acc_TB.vcd");
     $dumpvars(0, acc_TB); // Grabamos todo el contenido del TB
   end

endmodule

Acumulador/acc_TB.vcd
$date
	Mon Apr 20 15:17:50 2026
$end
$version
	Icarus Verilog
$end
$timescale
	1ms
$end
$scope module acc_TB $end
$var wire 4 ! count [3:0] $end
$var real 1 " DUTY_CYCLE $end
$var real 1 # OFFSET $end
$var real 1 $ PERIOD $end
$var reg 1 % add $end
$var reg 1 & clk $end
$var reg 1 ' reset $end
$var integer 32 ( i [31:0] $end
$scope module uut $end
$var wire 1 % add $end
$var wire 1 & clk $end
$var wire 1 ' reset $end
$var reg 4 ) count [3:0] $end
$upscope $end
$scope begin TEST_CASE $end
$upscope $end
$upscope $end
$enddefinitions $end
$comment Show the parameter values. $end
$dumpall
r1 $
r0.1 #
r0.5 "
$end
#0
$dumpvars
b0 )
bx (
0'
0&
0%
b0 !
$end
#500
1'
#600
1&
#1100
0'
0&
#1600
b1 !
b1 )
b0 (
1%
1&
#2100
0&
#2600
b10 !
b10 )
b1 (
1&
#3100
0&
#3600
b11 !
b11 )
b10 (
1&
#4100
0&
#4600
b100 !
b100 )
b11 (
1&
#5100
0&
#5600
b101 !
b101 )
b100 (
1&
#6100
0&
#6600
b110 !
b110 )
b101 (
1&
#7100
0&
#7600
b111 !
b111 )
b110 (
1&
#8100
0&
#8600
b1000 !
b1000 )
b111 (
1&
#9100
0&
#9600
b1001 !
b1001 )
b1000 (
1&
#10100
0&
#10600
b1010 !
b1010 )
b1001 (
1&
#11100
0&
#11600
0%
b1010 (
1&
