Calculadora/rtl/cores/Mult_32/Control_mult.v
module Control_mult (

    clk,
    rst,
    init,
    CONTROL,
    DONE,
    load_A,
    load_C,
    load_D,
    load_i,
    DSHT,
    done
);

input clk;
input rst;
input init;

input CONTROL;
input DONE;

output reg load_A;
output reg load_C;
output reg load_D;
output reg load_i;

output reg DSHT;
output reg done;

parameter S_INIT     = 4'd0;
parameter S_LOAD     = 4'd1;
parameter S_SLT_Ai   = 4'd2;
parameter S_COMP_Ai  = 4'd3;
parameter S_Ai0      = 4'd4;
parameter S_Ai1      = 4'd5;
parameter S_CHK_i    = 4'd6;
parameter S_ADDi_DS  = 4'd7;
parameter S_DONE     = 4'd8;

reg [3:0] state;
reg [3:0] next_state;

always @(posedge clk or posedge rst) begin

    if (rst)
        state <= S_INIT;

    else
        state <= next_state;

end

always @(*) begin

    case(state)

        S_INIT: begin

            if(init)
                next_state = S_LOAD;

            else
                next_state = S_INIT;

        end

        S_LOAD: begin

            next_state = S_SLT_Ai;

        end

        S_SLT_Ai: begin

            next_state = S_COMP_Ai;

        end

        S_COMP_Ai: begin

            if(CONTROL)
                next_state = S_Ai1;

            else
                next_state = S_Ai0;

        end

        S_Ai0: begin

            next_state = S_CHK_i;

        end

        S_Ai1: begin

            next_state = S_CHK_i;

        end

        S_CHK_i: begin

            if(DONE)
                next_state = S_DONE;

            else
                next_state = S_ADDi_DS;

        end

        S_ADDi_DS: begin

            next_state = S_SLT_Ai;

        end

        S_DONE: begin

            if(!init)
                next_state = S_INIT;

            else
                next_state = S_DONE;

        end

        default: begin

            next_state = S_INIT;

        end

    endcase

end

always @(*) begin

    load_A = 0;
    load_C = 0;
    load_D = 0;
    load_i = 0;
    DSHT = 0;
    done = 0;


    case(state)

        S_INIT: begin
        end

        S_LOAD: begin

            load_A = 1;
            load_D = 1;

        end

        S_SLT_Ai: begin
        end

        S_COMP_Ai: begin
        end

        S_Ai0: begin
        end

        S_Ai1: begin

            load_C = 1;

        end

        S_CHK_i: begin
        end


        S_ADDi_DS: begin

            load_i = 1;
            DSHT   = 1;

        end

        S_DONE: begin

            done = 1;

        end

        default: begin
        end

    endcase

end

endmodule

Calculadora/rtl/cores/Mult_32/ADD_D.v
module ADD_D (CONTROL, C_temp, D, C
);

input wire [15:0] D;
input wire [31:0] C;

input wire CONTROL;

output wire [31:0] C_temp;

assign C_temp = CONTROL ? (C + {16'b0, D}) : C;

endmodule

Multiplicador/Mult_32/Check_i.v
module Check_i(i, DONE);

input wire [3:0] i;

output DONE;

assign DONE = (i == 4'd15);

endmodule

Calculadora/rtl/cores/Mult_32/Comp_Ai.v
module Comp_Ai ( A, i, CONTROL
);

input wire [15:0] A;
input wire [3:0] i;

output wire CONTROL;

assign CONTROL = A[i];

endmodule

Paridad_9/Cont_i.v
module Cont_i (i_temp, i
);

input wire [3:0] i;

output wire [3:0] i_temp;

assign i_temp = i + 4'd1;

endmodule

Multiplicador/Mult_32/Reg_i.v
module Reg_i (rst, clk, load_i, i_temp, i
);

input rst;
input clk;
input load_i;
input [3:0]i_temp;

output reg[3:0]i;

always @(posedge clk) begin
    if (rst)
        i <= 4'b0000;

    else if (load_i)
        i <= i_temp;
end

endmodule

Calculadora/rtl/cores/Mult_32/Reg_C.v
module Reg_C (rst, clk, load_C, C_temp, C
);

input rst;
input clk;
input load_C;

input [31:0] C_temp;

output reg [31:0] C;

always @(posedge clk) begin
    if (rst)
        C <= 0;

    else if (load_C)
        C <= C_temp;
end

endmodule

Calculadora/rtl/cores/Mult_32/Reg_D.v
module Reg_D (rst, clk, load_D, DSHT, B, D
);

input rst;
input clk;
input load_D;
input DSHT;

input [15:0] B;

output reg [15:0] D;

always @(posedge clk) begin
    if (rst)
        D <= 16'b0;

    else if (load_D)
        D <= B;

    else if (DSHT)
        D <= D << 1;
end

endmodule

Multiplicador/Mult_32/Reg_A.v
module Reg_A (rst, clk, load_A, Ain, A
);

input rst;
input clk;
input load_A;

input [15:0] Ain;

output reg [15:0] A;

always @(posedge clk) begin
    if (rst)
        A <= 16'b0;

    else if (load_A)
        A <= Ain;
end

endmodule

Multiplicador/Mult_32/Mul_Top.v
module Mul_Top (

    clk,
    rst,
    init,

    Ain,
    B,

    C,
    done
);

input clk;
input rst;
input init;

input wire [15:0] Ain;
input wire [15:0] B;

output wire [31:0] C;
output wire done;

wire [15:0] A;
wire [15:0] D;

wire [31:0] C_temp;

wire [3:0] i;
wire [3:0] i_temp;

wire load_A;
wire load_C;
wire load_D;
wire load_i;

wire DSHT;

wire CONTROL;
wire DONE;

Reg_A RA (

    .rst(rst),
    .clk(clk),
    .load_A(load_A),

    .Ain(Ain),

    .A(A)

);

Reg_D RD (

    .rst(rst),
    .clk(clk),

    .load_D(load_D),
    .DSHT(DSHT),

    .B(B),

    .D(D)

);

Reg_C RC (

    .rst(rst),
    .clk(clk),

    .load_C(load_C),

    .C_temp(C_temp),

    .C(C)

);

Reg_i RI (

    .rst(rst),
    .clk(clk),

    .load_i(load_i),

    .i_temp(i_temp),

    .i(i)

);

Cont_i CI (

    .i_temp(i_temp),
    .i(i)

);

Comp_Ai CA (

    .A(A),
    .i(i),

    .CONTROL(CONTROL)

);

Check_i CHK (

    .i(i),

    .DONE(DONE)

);

ADD_D ADD (

    .CONTROL(CONTROL),

    .C_temp(C_temp),

    .D(D),
    .C(C)

);

Control_mult CTRL (

    .clk(clk),
    .rst(rst),

    .init(init),

    .CONTROL(CONTROL),
    .DONE(DONE),

    .load_A(load_A),
    .load_C(load_C),
    .load_D(load_D),
    .load_i(load_i),

    .DSHT(DSHT),

    .done(done)

);



endmodule

Multiplicador/Mult_32/Mul_Top_TB.v
`timescale 1ns / 1ps

module Mul_Top_TB;

reg clk;
reg rst;
reg init;

reg [15:0] Ain;
reg [15:0] B;

wire [31:0] C;
wire done;


//==================================
// INSTANCIA DEL DUT
//==================================

Mul_Top uut (

    .clk(clk),
    .rst(rst),
    .init(init),

    .Ain(Ain),
    .B(B),

    .C(C),
    .done(done)

);



//==================================
// PARAMETROS DE RELOJ
//==================================

parameter PERIOD = 20;
parameter real DUTY_CYCLE = 0.5;



//==================================
// GENERACION DEL CLOCK
//==================================

initial begin

    clk = 0;

    forever begin

        #(PERIOD*(1.0-DUTY_CYCLE))
        clk = ~clk;

        #(PERIOD*DUTY_CYCLE)
        clk = ~clk;

    end

end



//==================================
// ESTIMULOS
//==================================

initial begin

    //==============================
    // VALORES INICIALES
    //==============================

    rst  = 1;
    init = 0;

    Ain = 16'd5;
    B   = 16'd3;

    
    //==============================
    // RESET
    //==============================

    #40;
    rst = 0;


    //==============================
    // INICIO DE MULTIPLICACION
    //==============================

    @(posedge clk);

    init = 1;

    @(posedge clk);

    init = 0;


    //==============================
    // ESPERAR FINALIZACION
    //==============================

    wait(done);


    //==============================
    // MOSTRAR RESULTADO
    //==============================

    $display("=================================");
    $display("A = %d", Ain);
    $display("B = %d", B);
    $display("Resultado = %d", C);
    $display("=================================");


    //==============================
    // FINALIZAR SIMULACION
    //==============================

    #50;
    $finish;

end



//==================================
// GENERACION DE VCD
//==================================

initial begin

    $dumpfile("Mul_Top_TB.vcd");
    $dumpvars(0, Mul_Top_TB);

end

endmodule

Multiplicador/Mult_32/Mul_Top_TB.vcd
$date
	Sat May 23 23:17:00 2026
$end
$version
	Icarus Verilog
$end
$timescale
	1ps
$end
$scope module Mul_Top_TB $end
$var wire 1 ! done $end
$var wire 32 " C [31:0] $end
$var real 1 # DUTY_CYCLE $end
$var parameter 32 $ PERIOD $end
$var reg 16 % Ain [15:0] $end
$var reg 16 & B [15:0] $end
$var reg 1 ' clk $end
$var reg 1 ( init $end
$var reg 1 ) rst $end
$scope module uut $end
$var wire 16 * Ain [15:0] $end
$var wire 16 + B [15:0] $end
$var wire 1 ' clk $end
$var wire 1 ( init $end
$var wire 1 ) rst $end
$var wire 1 , load_i $end
$var wire 1 - load_D $end
$var wire 1 . load_C $end
$var wire 1 / load_A $end
$var wire 4 0 i_temp [3:0] $end
$var wire 4 1 i [3:0] $end
$var wire 1 ! done $end
$var wire 1 2 DSHT $end
$var wire 1 3 DONE $end
$var wire 16 4 D [15:0] $end
$var wire 32 5 C_temp [31:0] $end
$var wire 1 6 CONTROL $end
$var wire 32 7 C [31:0] $end
$var wire 16 8 A [15:0] $end
$scope module ADD $end
$var wire 16 9 D [15:0] $end
$var wire 32 : C_temp [31:0] $end
$var wire 1 6 CONTROL $end
$var wire 32 ; C [31:0] $end
$upscope $end
$scope module CA $end
$var wire 4 < i [3:0] $end
$var wire 1 6 CONTROL $end
$var wire 16 = A [15:0] $end
$upscope $end
$scope module CHK $end
$var wire 4 > i [3:0] $end
$var wire 1 3 DONE $end
$upscope $end
$scope module CI $end
$var wire 4 ? i_temp [3:0] $end
$var wire 4 @ i [3:0] $end
$upscope $end
$scope module CTRL $end
$var wire 1 6 CONTROL $end
$var wire 1 3 DONE $end
$var wire 1 ' clk $end
$var wire 1 ( init $end
$var wire 1 ) rst $end
$var parameter 4 A S_ADDi_DS $end
$var parameter 4 B S_Ai0 $end
$var parameter 4 C S_Ai1 $end
$var parameter 4 D S_CHK_i $end
$var parameter 4 E S_COMP_Ai $end
$var parameter 4 F S_DONE $end
$var parameter 4 G S_INIT $end
$var parameter 4 H S_LOAD $end
$var parameter 4 I S_SLT_Ai $end
$var reg 1 2 DSHT $end
$var reg 1 ! done $end
$var reg 1 / load_A $end
$var reg 1 . load_C $end
$var reg 1 - load_D $end
$var reg 1 , load_i $end
$var reg 4 J next_state [3:0] $end
$var reg 4 K state [3:0] $end
$upscope $end
$scope module RA $end
$var wire 16 L Ain [15:0] $end
$var wire 1 ' clk $end
$var wire 1 / load_A $end
$var wire 1 ) rst $end
$var reg 16 M A [15:0] $end
$upscope $end
$scope module RC $end
$var wire 32 N C_temp [31:0] $end
$var wire 1 ' clk $end
$var wire 1 . load_C $end
$var wire 1 ) rst $end
$var reg 32 O C [31:0] $end
$upscope $end
$scope module RD $end
$var wire 16 P B [15:0] $end
$var wire 1 2 DSHT $end
$var wire 1 ' clk $end
$var wire 1 - load_D $end
$var wire 1 ) rst $end
$var reg 16 Q D [15:0] $end
$upscope $end
$scope module RI $end
$var wire 1 ' clk $end
$var wire 4 R i_temp [3:0] $end
$var wire 1 , load_i $end
$var wire 1 ) rst $end
$var reg 4 S i [3:0] $end
$upscope $end
$upscope $end
$upscope $end
$enddefinitions $end
$comment Show the parameter values. $end
$dumpall
b10 I
b1 H
b0 G
b1000 F
b11 E
b110 D
b101 C
b100 B
b111 A
b10100 $
r0.5 #
$end
#0
$dumpvars
bx S
bx R
bx Q
b11 P
bx O
bx N
bx M
b101 L
b0 K
b0 J
bx @
bx ?
bx >
bx =
bx <
bx ;
bx :
bx 9
bx 8
bx 7
x6
bx 5
bx 4
x3
02
bx 1
bx 0
0/
0.
0-
0,
b11 +
b101 *
1)
0(
0'
b11 &
b101 %
bx "
0!
$end
#10000
b0 5
b0 :
b0 N
06
b0 8
b0 =
b0 M
b0 4
b0 9
b0 Q
b0 "
b0 7
b0 ;
b0 O
b1 0
b1 ?
b1 R
03
b0 1
b0 <
b0 >
b0 @
b0 S
1'
#20000
0'
#30000
1'
#40000
0'
0)
#50000
b1 J
1(
1'
#60000
0'
#70000
1-
1/
b1 K
b10 J
0(
1'
#80000
0'
#90000
0-
0/
b11 5
b11 :
b11 N
b11 J
b10 K
16
b101 8
b101 =
b101 M
b11 4
b11 9
b11 Q
1'
#100000
0'
#110000
b101 J
b11 K
1'
#120000
0'
#130000
1.
b110 J
b101 K
1'
#140000
0'
#150000
0.
b111 J
b110 5
b110 :
b110 N
b110 K
b11 "
b11 7
b11 ;
b11 O
1'
#160000
0'
#170000
12
1,
b10 J
b111 K
1'
#180000
0'
#190000
02
0,
b11 J
b11 5
b11 :
b11 N
b10 K
b10 0
b10 ?
b10 R
06
b1 1
b1 <
b1 >
b1 @
b1 S
b110 4
b110 9
b110 Q
1'
#200000
0'
#210000
b100 J
b11 K
1'
#220000
0'
#230000
b110 J
b100 K
1'
#240000
0'
#250000
b111 J
b110 K
1'
#260000
0'
#270000
12
1,
b10 J
b111 K
1'
#280000
0'
#290000
02
0,
b1111 5
b1111 :
b1111 N
b11 J
b10 K
b1100 4
b1100 9
b1100 Q
b11 0
b11 ?
b11 R
16
b10 1
b10 <
b10 >
b10 @
b10 S
1'
#300000
0'
#310000
b101 J
b11 K
1'
#320000
0'
#330000
1.
b110 J
b101 K
1'
#340000
0'
#350000
0.
b111 J
b11011 5
b11011 :
b11011 N
b110 K
b1111 "
b1111 7
b1111 ;
b1111 O
1'
#360000
0'
#370000
12
1,
b10 J
b111 K
1'
#380000
0'
#390000
02
0,
b11 J
b1111 5
b1111 :
b1111 N
b10 K
b100 0
b100 ?
b100 R
06
b11 1
b11 <
b11 >
b11 @
b11 S
b11000 4
b11000 9
b11000 Q
1'
#400000
0'
#410000
b100 J
b11 K
1'
#420000
0'
#430000
b110 J
b100 K
1'
#440000
0'
#450000
b111 J
b110 K
1'
#460000
0'
#470000
12
1,
b10 J
b111 K
1'
#480000
0'
#490000
02
0,
b11 J
b10 K
b110000 4
b110000 9
b110000 Q
b101 0
b101 ?
b101 R
b100 1
b100 <
b100 >
b100 @
b100 S
1'
#500000
0'
#510000
b100 J
b11 K
1'
#520000
0'
#530000
b110 J
b100 K
1'
#540000
0'
#550000
b111 J
b110 K
1'
#560000
0'
#570000
12
1,
b10 J
b111 K
1'
#580000
0'
#590000
02
0,
b11 J
b10 K
b110 0
b110 ?
b110 R
b101 1
b101 <
b101 >
b101 @
b101 S
b1100000 4
b1100000 9
b1100000 Q
1'
#600000
0'
#610000
b100 J
b11 K
1'
#620000
0'
#630000
b110 J
b100 K
1'
#640000
0'
#650000
b111 J
b110 K
1'
#660000
0'
#670000
12
1,
b10 J
b111 K
1'
#680000
0'
#690000
02
0,
b11 J
b10 K
b11000000 4
b11000000 9
b11000000 Q
b111 0
b111 ?
b111 R
b110 1
b110 <
b110 >
b110 @
b110 S
1'
#700000
0'
#710000
b100 J
b11 K
1'
#720000
0'
#730000
b110 J
b100 K
1'
#740000
0'
#750000
b111 J
b110 K
1'
#760000
0'
#770000
12
1,
b10 J
b111 K
1'
#780000
0'
#790000
02
0,
b11 J
b10 K
b1000 0
b1000 ?
b1000 R
b111 1
b111 <
b111 >
b111 @
b111 S
b110000000 4
b110000000 9
b110000000 Q
1'
#800000
0'
#810000
b100 J
b11 K
1'
#820000
0'
#830000
b110 J
b100 K
1'
#840000
0'
#850000
b111 J
b110 K
1'
#860000
0'
#870000
12
1,
b10 J
b111 K
1'
#880000
0'
#890000
02
0,
b11 J
b10 K
b1100000000 4
b1100000000 9
b1100000000 Q
b1001 0
b1001 ?
b1001 R
b1000 1
b1000 <
b1000 >
b1000 @
b1000 S
1'
#900000
0'
#910000
b100 J
b11 K
1'
#920000
0'
#930000
b110 J
b100 K
1'
#940000
0'
#950000
b111 J
b110 K
1'
#960000
0'
#970000
12
1,
b10 J
b111 K
1'
#980000
0'
#990000
02
0,
b11 J
b10 K
b1010 0
b1010 ?
b1010 R
b1001 1
b1001 <
b1001 >
b1001 @
b1001 S
b11000000000 4
b11000000000 9
b11000000000 Q
1'
#1000000
0'
#1010000
b100 J
b11 K
1'
#1020000
0'
#1030000
b110 J
b100 K
1'
#1040000
0'
#1050000
b111 J
b110 K
1'
#1060000
0'
#1070000
12
1,
b10 J
b111 K
1'
#1080000
0'
#1090000
02
0,
b11 J
b10 K
b110000000000 4
b110000000000 9
b110000000000 Q
b1011 0
b1011 ?
b1011 R
b1010 1
b1010 <
b1010 >
b1010 @
b1010 S
1'
#1100000
0'
#1110000
b100 J
b11 K
1'
#1120000
0'
#1130000
b110 J
b100 K
1'
#1140000
0'
#1150000
b111 J
b110 K
1'
#1160000
0'
#1170000
12
1,
b10 J
b111 K
1'
#1180000
0'
#1190000
02
0,
b11 J
b10 K
b1100 0
b1100 ?
b1100 R
b1011 1
b1011 <
b1011 >
b1011 @
b1011 S
b1100000000000 4
b1100000000000 9
b1100000000000 Q
1'
#1200000
0'
#1210000
b100 J
b11 K
1'
#1220000
0'
#1230000
b110 J
b100 K
1'
#1240000
0'
#1250000
b111 J
b110 K
1'
#1260000
0'
#1270000
12
1,
b10 J
b111 K
1'
#1280000
0'
#1290000
02
0,
b11 J
b10 K
b11000000000000 4
b11000000000000 9
b11000000000000 Q
b1101 0
b1101 ?
b1101 R
b1100 1
b1100 <
b1100 >
b1100 @
b1100 S
1'
#1300000
0'
#1310000
b100 J
b11 K
1'
#1320000
0'
#1330000
b110 J
b100 K
1'
#1340000
0'
#1350000
b111 J
b110 K
1'
#1360000
0'
#1370000
12
1,
b10 J
b111 K
1'
#1380000
0'
#1390000
02
0,
b11 J
b10 K
b1110 0
b1110 ?
b1110 R
b1101 1
b1101 <
b1101 >
b1101 @
b1101 S
b110000000000000 4
b110000000000000 9
b110000000000000 Q
1'
#1400000
0'
#1410000
b100 J
b11 K
1'
#1420000
0'
#1430000
b110 J
b100 K
1'
#1440000
0'
#1450000
b111 J
b110 K
1'
#1460000
0'
#1470000
12
1,
b10 J
b111 K
1'
#1480000
0'
#1490000
02
0,
b11 J
b10 K
b1100000000000000 4
b1100000000000000 9
b1100000000000000 Q
b1111 0
b1111 ?
b1111 R
b1110 1
b1110 <
b1110 >
b1110 @
b1110 S
1'
#1500000
0'
#1510000
b100 J
b11 K
1'
#1520000
0'
#1530000
b110 J
b100 K
1'
#1540000
0'
#1550000
b111 J
b110 K
1'
#1560000
0'
#1570000
12
1,
b10 J
b111 K
1'
#1580000
0'
#1590000
02
0,
b11 J
b10 K
b0 0
b0 ?
b0 R
13
b1111 1
b1111 <
b1111 >
b1111 @
b1111 S
b1000000000000000 4
b1000000000000000 9
b1000000000000000 Q
1'
#1600000
0'
#1610000
b100 J
b11 K
1'
#1620000
0'
#1630000
b110 J
b100 K
1'
#1640000
0'
#1650000
b1000 J
b110 K
1'
#1660000
0'
#1670000
1!
b0 J
b1000 K
1'
#1680000
0'
#1690000
0!
b0 K
1'
