BCD/BINtoBCD_32/Control_BCD.v
module Control_BCD (

    clk,
    rst,
    init,

    DONE,

    load_BCD,
    load_B,
    load_i,

    done

);

input clk;
input rst;
input init;

input DONE;

output reg load_BCD;
output reg load_B;
output reg load_i;

output reg done;


parameter S_INIT    = 3'd0;
parameter S_LOAD    = 3'd1;
parameter S_PROCESS = 3'd2;
parameter S_CHK_i   = 3'd3;
parameter S_DONE    = 3'd4;


reg [2:0] state;
reg [2:0] next_state;

reg [3:0] done_count;


always @(posedge clk or posedge rst) begin

    if(rst) begin

        state <= S_INIT;
        done_count <= 4'd0;

    end

    else begin

        state <= next_state;

        if(state == S_DONE)
            done_count <= done_count + 1'b1;

        else
            done_count <= 4'd0;

    end

end



always @(*) begin

    case(state)

        S_INIT: begin

            if(init)
                next_state = S_LOAD;

            else
                next_state = S_INIT;

        end


        S_LOAD: begin

            next_state = S_PROCESS;

        end


        S_PROCESS: begin

            next_state = S_CHK_i;

        end


        S_CHK_i: begin

            if(DONE)
                next_state = S_DONE;

            else
                next_state = S_PROCESS;

        end


        S_DONE: begin

            if(done_count == 4'd15)
                next_state = S_INIT;

            else
                next_state = S_DONE;

        end


        default: begin

            next_state = S_INIT;

        end

    endcase

end



always @(*) begin

    load_BCD = 1'b0;
    load_B   = 1'b0;
    load_i   = 1'b0;

    done     = 1'b0;


    case(state)

        S_INIT: begin
        end


        S_LOAD: begin
            // init se conecta directamente
            // a Reg_BCD, Reg_B y Reg_i
        end


        S_PROCESS: begin

            load_BCD = 1'b1;
            load_B   = 1'b1;
            load_i   = 1'b1;

        end


        S_CHK_i: begin
        end


        S_DONE: begin

            done = 1'b1;

        end


        default: begin
        end

    endcase

end

endmodule

BCD/BCDtoBIN_32/Check_i.v
module Check_i (i, DONE
);

input wire [5:0] i;

output DONE;

assign DONE = (i == 6'd0);

endmodule

BCD/BCDtoBIN_32/Rest_i.v
module Rest_i (i_temp, i
);

input wire [5:0] i;

output wire [5:0] i_temp;

assign i_temp = i - 6'd1;

endmodule

BCD/BCDtoBIN_32/Conc_BCD.v
module Conc_BCD (
    BCD_add,
    B,
    BCD_temp
);

input  [39:0] BCD_add;
input  [31:0] B;

output [39:0] BCD_temp;

assign BCD_temp = {BCD_add[38:0], B[31]};

endmodule

BCD/BINtoBCD_32/SHT_B.v
module SHT_B (
    B,
    B_sht
);

input [31:0]B;
output [31:0] B_sht;

assign B_sht = B << 1;
    
endmodule

BCD/BCDtoBIN_32/Add3._BCD.v
module Add3_BCD (
    input  [39:0] BCD,
    output [39:0] BCD_add
);

assign BCD_add[3:0] =
    (BCD[3:0] >= 4'd5) ?
    BCD[3:0] + 4'd3 :
    BCD[3:0];

assign BCD_add[7:4] =
    (BCD[7:4] >= 4'd5) ?
    BCD[7:4] + 4'd3 :
    BCD[7:4];

assign BCD_add[11:8] =
    (BCD[11:8] >= 4'd5) ?
    BCD[11:8] + 4'd3 :
    BCD[11:8];

assign BCD_add[15:12] =
    (BCD[15:12] >= 4'd5) ?
    BCD[15:12] + 4'd3 :
    BCD[15:12];

assign BCD_add[19:16] =
    (BCD[19:16] >= 4'd5) ?
    BCD[19:16] + 4'd3 :
    BCD[19:16];

assign BCD_add[23:20] =
    (BCD[23:20] >= 4'd5) ?
    BCD[23:20] + 4'd3 :
    BCD[23:20];

assign BCD_add[27:24] =
    (BCD[27:24] >= 4'd5) ?
    BCD[27:24] + 4'd3 :
    BCD[27:24];

assign BCD_add[31:28] =
    (BCD[31:28] >= 4'd5) ?
    BCD[31:28] + 4'd3 :
    BCD[31:28];

assign BCD_add[35:32] =
    (BCD[35:32] >= 4'd5) ?
    BCD[35:32] + 4'd3 :
    BCD[35:32];

assign BCD_add[39:36] =
    (BCD[39:36] >= 4'd5) ?
    BCD[39:36] + 4'd3 :
    BCD[39:36];

endmodule

BCD/BCDtoBIN_32/Reg_i.v
module Reg_i (rst, clk, load_i, i_temp, i, init
);

input rst;
input clk;
input load_i;
input init;

input [5:0] i_temp;

output reg [5:0] i;

always @(posedge clk or posedge rst) begin

    if (rst)
        i <= 6'b0;

    else if (init)

        i <= 6'd32;

    else if (load_i)
        i <= i_temp;

end

endmodule

BCD/BCDtoBIN_32/Reg_B.v
module Reg_B (rst, clk, init, load_B, Bin, B_temp, B
);

input rst;
input clk;
input load_B;
input init;
input [31:0] Bin;
input [31:0] B_temp;

output reg [31:0] B;

always @(posedge clk or posedge rst) begin

    if (rst)
        B <= 32'b0;

    else if (init)

        B <= Bin;

    else if (load_B)
        B <= B_temp;
end

endmodule

Calculadora/rtl/cores/BINtoBCD_32/Reg_BCD.v
module Reg_BCD (
    input rst,
    input clk,
    input load_BCD,
    input init,
    input [39:0] BCD_temp,

    output reg [39:0] BCD
);

always @(posedge clk or posedge rst) begin

    if (rst)
        BCD <= 40'b0;

    else if (init)
        BCD <= 40'b0;

    else if (load_BCD)
        BCD <= BCD_temp;

end

endmodule

BCD/BCDtoBIN_32/BCD_Top.v
module BCD_TOP (

    clk,
    rst,
    init,

    Bin,

    BCD,

    done

);

input clk;
input rst;
input init;

input wire [31:0] Bin;

output wire [39:0] BCD;

output wire done;


/*========================
=         WIRES          =
========================*/

wire [39:0] BCD_add;
wire [39:0] BCD_temp;

wire [31:0] B;
wire [31:0] B_temp;

wire [5:0] i;
wire [5:0] i_temp;

wire DONE;

wire load_BCD;
wire load_B;
wire load_i;


/*========================
=       REGISTERS        =
========================*/

Reg_BCD RBCD (

    .rst(rst),
    .clk(clk),

    .init(init),

    .load_BCD(load_BCD),

    .BCD_temp(BCD_temp),

    .BCD(BCD)

);


Reg_B RB (

    .rst(rst),
    .clk(clk),

    .init(init),

    .load_B(load_B),

    .Bin(Bin),

    .B_temp(B_temp),

    .B(B)

);


Reg_i RI (

    .rst(rst),
    .clk(clk),

    .init(init),

    .load_i(load_i),

    .i_temp(i_temp),

    .i(i)

);


/*========================
=    COMBINATIONAL       =
========================*/

Add3_BCD ADD3 (

    .BCD(BCD),

    .BCD_add(BCD_add)

);


SHT_B SHB (

    .B(B),

    .B_sht(B_temp)

);


Conc_BCD CONC (

    .BCD_add(BCD_add),

    .B(B),

    .BCD_temp(BCD_temp)

);


Rest_i RESTI (

    .i(i),

    .i_temp(i_temp)

);


Check_i CHKI (

    .i(i),

    .DONE(DONE)

);


/*========================
=        CONTROL         =
========================*/

Control_BCD CTRL (

    .clk(clk),
    .rst(rst),

    .init(init),

    .DONE(DONE),

    .load_BCD(load_BCD),
    .load_B(load_B),
    .load_i(load_i),

    .done(done)

);

endmodule

BCD/BCDtoBIN_32/BCD_TOP_TB.v
`timescale 1ns / 1ps

module BCD_TOP_TB;

reg clk;
reg rst;
reg init;

reg [31:0] Bin;

wire [39:0] BCD;

wire done;



//==================================
// INSTANCIA DEL DUT
//==================================

BCD_TOP uut (

    .clk(clk),
    .rst(rst),
    .init(init),

    .Bin(Bin),

    .BCD(BCD),

    .done(done)

);



//==================================
// PARAMETROS DE RELOJ
//==================================

parameter PERIOD = 20;
parameter real DUTY_CYCLE = 0.5;



//==================================
// GENERACION DEL CLOCK
//==================================

initial begin

    clk = 0;

    forever begin

        #(PERIOD*(1.0-DUTY_CYCLE))
        clk = ~clk;

        #(PERIOD*DUTY_CYCLE)
        clk = ~clk;

    end

end



//==================================
// ESTIMULOS
//==================================

initial begin

    //==============================
    // VALORES INICIALES
    //==============================

    rst  = 1;
    init = 0;

    Bin = 32'd123;


    //==============================
    // RESET
    //==============================

    #40;
    rst = 0;


    //==============================
    // INICIO CONVERSION
    //==============================

    @(posedge clk);

    init = 1;

    @(posedge clk);

    init = 0;


    //==============================
    // ESPERAR FINALIZACION
    //==============================

    wait(done);


    //==============================
    // MOSTRAR RESULTADO
    //==============================

    $display("=================================");
    $display("Binario = %d", Bin);

    $display("BCD[39:36] = %d", BCD[39:36]);
    $display("BCD[35:32] = %d", BCD[35:32]);
    $display("BCD[31:28] = %d", BCD[31:28]);
    $display("BCD[27:24] = %d", BCD[27:24]);
    $display("BCD[23:20] = %d", BCD[23:20]);
    $display("BCD[19:16] = %d", BCD[19:16]);
    $display("BCD[15:12] = %d", BCD[15:12]);
    $display("BCD[11:8]  = %d", BCD[11:8]);
    $display("BCD[7:4]   = %d", BCD[7:4]);
    $display("BCD[3:0]   = %d", BCD[3:0]);

    $display("=================================");


    //==============================
    // FINALIZAR SIMULACION
    //==============================

    #50;
    $finish;

end



//==================================
// GENERACION DE VCD
//==================================

initial begin

    $dumpfile("BCD_TOP_TB.vcd");
    $dumpvars(0, BCD_TOP_TB);

end

endmodule

BCD/BCDtoBIN_32/BCD_TOP_TB.vcd
$date
	Thu Jun 18 01:37:56 2026
$end
$version
	Icarus Verilog
$end
$timescale
	1ps
$end
$scope module BCD_TOP_TB $end
$var wire 1 ! done $end
$var wire 40 " BCD [39:0] $end
$var real 1 # DUTY_CYCLE $end
$var parameter 32 $ PERIOD $end
$var reg 32 % Bin [31:0] $end
$var reg 1 & clk $end
$var reg 1 ' init $end
$var reg 1 ( rst $end
$scope module uut $end
$var wire 32 ) Bin [31:0] $end
$var wire 1 & clk $end
$var wire 1 ' init $end
$var wire 1 ( rst $end
$var wire 1 * load_i $end
$var wire 1 + load_BCD $end
$var wire 1 , load_B $end
$var wire 6 - i_temp [5:0] $end
$var wire 6 . i [5:0] $end
$var wire 1 ! done $end
$var wire 1 / DONE $end
$var wire 32 0 B_temp [31:0] $end
$var wire 40 1 BCD_temp [39:0] $end
$var wire 40 2 BCD_add [39:0] $end
$var wire 40 3 BCD [39:0] $end
$var wire 32 4 B [31:0] $end
$scope module ADD3 $end
$var wire 40 5 BCD_add [39:0] $end
$var wire 40 6 BCD [39:0] $end
$upscope $end
$scope module CHKI $end
$var wire 6 7 i [5:0] $end
$var wire 1 / DONE $end
$upscope $end
$scope module CONC $end
$var wire 40 8 BCD_add [39:0] $end
$var wire 40 9 BCD_temp [39:0] $end
$var wire 32 : B [31:0] $end
$upscope $end
$scope module CTRL $end
$var wire 1 / DONE $end
$var wire 1 & clk $end
$var wire 1 ' init $end
$var wire 1 ( rst $end
$var parameter 3 ; S_CHK_i $end
$var parameter 3 < S_DONE $end
$var parameter 3 = S_INIT $end
$var parameter 3 > S_LOAD $end
$var parameter 3 ? S_PROCESS $end
$var reg 1 ! done $end
$var reg 4 @ done_count [3:0] $end
$var reg 1 , load_B $end
$var reg 1 + load_BCD $end
$var reg 1 * load_i $end
$var reg 3 A next_state [2:0] $end
$var reg 3 B state [2:0] $end
$upscope $end
$scope module RB $end
$var wire 32 C Bin [31:0] $end
$var wire 1 & clk $end
$var wire 1 ' init $end
$var wire 1 , load_B $end
$var wire 1 ( rst $end
$var wire 32 D B_temp [31:0] $end
$var reg 32 E B [31:0] $end
$upscope $end
$scope module RBCD $end
$var wire 40 F BCD_temp [39:0] $end
$var wire 1 & clk $end
$var wire 1 ' init $end
$var wire 1 + load_BCD $end
$var wire 1 ( rst $end
$var reg 40 G BCD [39:0] $end
$upscope $end
$scope module RESTI $end
$var wire 6 H i_temp [5:0] $end
$var wire 6 I i [5:0] $end
$upscope $end
$scope module RI $end
$var wire 1 & clk $end
$var wire 6 J i_temp [5:0] $end
$var wire 1 ' init $end
$var wire 1 * load_i $end
$var wire 1 ( rst $end
$var reg 6 K i [5:0] $end
$upscope $end
$scope module SHB $end
$var wire 32 L B [31:0] $end
$var wire 32 M B_sht [31:0] $end
$upscope $end
$upscope $end
$upscope $end
$enddefinitions $end
$comment Show the parameter values. $end
$dumpall
b10 ?
b1 >
b0 =
b100 <
b11 ;
b10100 $
r0.5 #
$end
#0
$dumpvars
b0 M
b0 L
b0 K
b111111 J
b0 I
b111111 H
b0 G
b0 F
b0 E
b0 D
b1111011 C
b0 B
b0 A
b0 @
b0 :
b0 9
b0 8
b0 7
b0 6
b0 5
b0 4
b0 3
b0 2
b0 1
b0 0
1/
b0 .
b111111 -
0,
0+
0*
b1111011 )
1(
0'
0&
b1111011 %
b0 "
0!
$end
#10000
1&
#20000
0&
#30000
1&
#40000
0&
0(
#50000
b11110110 0
b11110110 D
b11110110 M
b11111 -
b11111 H
b11111 J
0/
b100000 .
b100000 7
b100000 I
b100000 K
b1111011 4
b1111011 :
b1111011 E
b1111011 L
b1 A
1'
1&
#60000
0&
#70000
b1 B
b10 A
0'
1&
#80000
0&
#90000
1*
1,
1+
b11 A
b10 B
1&
#100000
0&
#110000
b111101100 0
b111101100 D
b111101100 M
0*
0,
0+
b10 A
b11110110 4
b11110110 :
b11110110 E
b11110110 L
b11110 -
b11110 H
b11110 J
b11111 .
b11111 7
b11111 I
b11111 K
b11 B
1&
#120000
0&
#130000
1*
1,
1+
b11 A
b10 B
1&
#140000
0&
#150000
b1111011000 0
b1111011000 D
b1111011000 M
0*
0,
0+
b10 A
b111101100 4
b111101100 :
b111101100 E
b111101100 L
b11101 -
b11101 H
b11101 J
b11110 .
b11110 7
b11110 I
b11110 K
b11 B
1&
#160000
0&
#170000
1*
1,
1+
b11 A
b10 B
1&
#180000
0&
#190000
b11110110000 0
b11110110000 D
b11110110000 M
0*
0,
0+
b10 A
b1111011000 4
b1111011000 :
b1111011000 E
b1111011000 L
b11100 -
b11100 H
b11100 J
b11101 .
b11101 7
b11101 I
b11101 K
b11 B
1&
#200000
0&
#210000
1*
1,
1+
b11 A
b10 B
1&
#220000
0&
#230000
b111101100000 0
b111101100000 D
b111101100000 M
0*
0,
0+
b10 A
b11110110000 4
b11110110000 :
b11110110000 E
b11110110000 L
b11011 -
b11011 H
b11011 J
b11100 .
b11100 7
b11100 I
b11100 K
b11 B
1&
#240000
0&
#250000
1*
1,
1+
b11 A
b10 B
1&
#260000
0&
#270000
b1111011000000 0
b1111011000000 D
b1111011000000 M
0*
0,
0+
b10 A
b111101100000 4
b111101100000 :
b111101100000 E
b111101100000 L
b11010 -
b11010 H
b11010 J
b11011 .
b11011 7
b11011 I
b11011 K
b11 B
1&
#280000
0&
#290000
1*
1,
1+
b11 A
b10 B
1&
#300000
0&
#310000
b11110110000000 0
b11110110000000 D
b11110110000000 M
0*
0,
0+
b10 A
b1111011000000 4
b1111011000000 :
b1111011000000 E
b1111011000000 L
b11001 -
b11001 H
b11001 J
b11010 .
b11010 7
b11010 I
b11010 K
b11 B
1&
#320000
0&
#330000
1*
1,
1+
b11 A
b10 B
1&
#340000
0&
#350000
b111101100000000 0
b111101100000000 D
b111101100000000 M
0*
0,
0+
b10 A
b11110110000000 4
b11110110000000 :
b11110110000000 E
b11110110000000 L
b11000 -
b11000 H
b11000 J
b11001 .
b11001 7
b11001 I
b11001 K
b11 B
1&
#360000
0&
#370000
1*
1,
1+
b11 A
b10 B
1&
#380000
0&
#390000
b1111011000000000 0
b1111011000000000 D
b1111011000000000 M
0*
0,
0+
b10 A
b111101100000000 4
b111101100000000 :
b111101100000000 E
b111101100000000 L
b10111 -
b10111 H
b10111 J
b11000 .
b11000 7
b11000 I
b11000 K
b11 B
1&
#400000
0&
#410000
1*
1,
1+
b11 A
b10 B
1&
#420000
0&
#430000
b11110110000000000 0
b11110110000000000 D
b11110110000000000 M
0*
0,
0+
b10 A
b1111011000000000 4
b1111011000000000 :
b1111011000000000 E
b1111011000000000 L
b10110 -
b10110 H
b10110 J
b10111 .
b10111 7
b10111 I
b10111 K
b11 B
1&
#440000
0&
#450000
1*
1,
1+
b11 A
b10 B
1&
#460000
0&
#470000
b111101100000000000 0
b111101100000000000 D
b111101100000000000 M
0*
0,
0+
b10 A
b11110110000000000 4
b11110110000000000 :
b11110110000000000 E
b11110110000000000 L
b10101 -
b10101 H
b10101 J
b10110 .
b10110 7
b10110 I
b10110 K
b11 B
1&
#480000
0&
#490000
1*
1,
1+
b11 A
b10 B
1&
#500000
0&
#510000
b1111011000000000000 0
b1111011000000000000 D
b1111011000000000000 M
0*
0,
0+
b10 A
b111101100000000000 4
b111101100000000000 :
b111101100000000000 E
b111101100000000000 L
b10100 -
b10100 H
b10100 J
b10101 .
b10101 7
b10101 I
b10101 K
b11 B
1&
#520000
0&
#530000
1*
1,
1+
b11 A
b10 B
1&
#540000
0&
#550000
b11110110000000000000 0
b11110110000000000000 D
b11110110000000000000 M
0*
0,
0+
b10 A
b1111011000000000000 4
b1111011000000000000 :
b1111011000000000000 E
b1111011000000000000 L
b10011 -
b10011 H
b10011 J
b10100 .
b10100 7
b10100 I
b10100 K
b11 B
1&
#560000
0&
#570000
1*
1,
1+
b11 A
b10 B
1&
#580000
0&
#590000
b111101100000000000000 0
b111101100000000000000 D
b111101100000000000000 M
0*
0,
0+
b10 A
b11110110000000000000 4
b11110110000000000000 :
b11110110000000000000 E
b11110110000000000000 L
b10010 -
b10010 H
b10010 J
b10011 .
b10011 7
b10011 I
b10011 K
b11 B
1&
#600000
0&
#610000
1*
1,
1+
b11 A
b10 B
1&
#620000
0&
#630000
b1111011000000000000000 0
b1111011000000000000000 D
b1111011000000000000000 M
0*
0,
0+
b10 A
b111101100000000000000 4
b111101100000000000000 :
b111101100000000000000 E
b111101100000000000000 L
b10001 -
b10001 H
b10001 J
b10010 .
b10010 7
b10010 I
b10010 K
b11 B
1&
#640000
0&
#650000
1*
1,
1+
b11 A
b10 B
1&
#660000
0&
#670000
b11110110000000000000000 0
b11110110000000000000000 D
b11110110000000000000000 M
0*
0,
0+
b10 A
b1111011000000000000000 4
b1111011000000000000000 :
b1111011000000000000000 E
b1111011000000000000000 L
b10000 -
b10000 H
b10000 J
b10001 .
b10001 7
b10001 I
b10001 K
b11 B
1&
#680000
0&
#690000
1*
1,
1+
b11 A
b10 B
1&
#700000
0&
#710000
b111101100000000000000000 0
b111101100000000000000000 D
b111101100000000000000000 M
0*
0,
0+
b10 A
b11110110000000000000000 4
b11110110000000000000000 :
b11110110000000000000000 E
b11110110000000000000000 L
b1111 -
b1111 H
b1111 J
b10000 .
b10000 7
b10000 I
b10000 K
b11 B
1&
#720000
0&
#730000
1*
1,
1+
b11 A
b10 B
1&
#740000
0&
#750000
b1111011000000000000000000 0
b1111011000000000000000000 D
b1111011000000000000000000 M
0*
0,
0+
b10 A
b111101100000000000000000 4
b111101100000000000000000 :
b111101100000000000000000 E
b111101100000000000000000 L
b1110 -
b1110 H
b1110 J
b1111 .
b1111 7
b1111 I
b1111 K
b11 B
1&
#760000
0&
#770000
1*
1,
1+
b11 A
b10 B
1&
#780000
0&
#790000
b11110110000000000000000000 0
b11110110000000000000000000 D
b11110110000000000000000000 M
0*
0,
0+
b10 A
b1111011000000000000000000 4
b1111011000000000000000000 :
b1111011000000000000000000 E
b1111011000000000000000000 L
b1101 -
b1101 H
b1101 J
b1110 .
b1110 7
b1110 I
b1110 K
b11 B
1&
#800000
0&
#810000
1*
1,
1+
b11 A
b10 B
1&
#820000
0&
#830000
b111101100000000000000000000 0
b111101100000000000000000000 D
b111101100000000000000000000 M
0*
0,
0+
b10 A
b11110110000000000000000000 4
b11110110000000000000000000 :
b11110110000000000000000000 E
b11110110000000000000000000 L
b1100 -
b1100 H
b1100 J
b1101 .
b1101 7
b1101 I
b1101 K
b11 B
1&
#840000
0&
#850000
1*
1,
1+
b11 A
b10 B
1&
#860000
0&
#870000
b1111011000000000000000000000 0
b1111011000000000000000000000 D
b1111011000000000000000000000 M
0*
0,
0+
b10 A
b111101100000000000000000000 4
b111101100000000000000000000 :
b111101100000000000000000000 E
b111101100000000000000000000 L
b1011 -
b1011 H
b1011 J
b1100 .
b1100 7
b1100 I
b1100 K
b11 B
1&
#880000
0&
#890000
1*
1,
1+
b11 A
b10 B
1&
#900000
0&
#910000
b11110110000000000000000000000 0
b11110110000000000000000000000 D
b11110110000000000000000000000 M
0*
0,
0+
b10 A
b1111011000000000000000000000 4
b1111011000000000000000000000 :
b1111011000000000000000000000 E
b1111011000000000000000000000 L
b1010 -
b1010 H
b1010 J
b1011 .
b1011 7
b1011 I
b1011 K
b11 B
1&
#920000
0&
#930000
1*
1,
1+
b11 A
b10 B
1&
#940000
0&
#950000
b111101100000000000000000000000 0
b111101100000000000000000000000 D
b111101100000000000000000000000 M
0*
0,
0+
b10 A
b11110110000000000000000000000 4
b11110110000000000000000000000 :
b11110110000000000000000000000 E
b11110110000000000000000000000 L
b1001 -
b1001 H
b1001 J
b1010 .
b1010 7
b1010 I
b1010 K
b11 B
1&
#960000
0&
#970000
1*
1,
1+
b11 A
b10 B
1&
#980000
0&
#990000
b1111011000000000000000000000000 0
b1111011000000000000000000000000 D
b1111011000000000000000000000000 M
0*
0,
0+
b10 A
b111101100000000000000000000000 4
b111101100000000000000000000000 :
b111101100000000000000000000000 E
b111101100000000000000000000000 L
b1000 -
b1000 H
b1000 J
b1001 .
b1001 7
b1001 I
b1001 K
b11 B
1&
#1000000
0&
#1010000
1*
1,
1+
b11 A
b10 B
1&
#1020000
0&
#1030000
b11110110000000000000000000000000 0
b11110110000000000000000000000000 D
b11110110000000000000000000000000 M
0*
0,
0+
b10 A
b1111011000000000000000000000000 4
b1111011000000000000000000000000 :
b1111011000000000000000000000000 E
b1111011000000000000000000000000 L
b111 -
b111 H
b111 J
b1000 .
b1000 7
b1000 I
b1000 K
b11 B
1&
#1040000
0&
#1050000
1*
1,
1+
b11 A
b10 B
1&
#1060000
0&
#1070000
b11101100000000000000000000000000 0
b11101100000000000000000000000000 D
b11101100000000000000000000000000 M
b1 1
b1 9
b1 F
0*
0,
0+
b10 A
b11110110000000000000000000000000 4
b11110110000000000000000000000000 :
b11110110000000000000000000000000 E
b11110110000000000000000000000000 L
b110 -
b110 H
b110 J
b111 .
b111 7
b111 I
b111 K
b11 B
1&
#1080000
0&
#1090000
1*
1,
1+
b11 A
b10 B
1&
#1100000
0&
#1110000
b11 1
b11 9
b11 F
b1 2
b1 5
b1 8
b11011000000000000000000000000000 0
b11011000000000000000000000000000 D
b11011000000000000000000000000000 M
0*
0,
0+
b10 A
b1 "
b1 3
b1 6
b1 G
b11101100000000000000000000000000 4
b11101100000000000000000000000000 :
b11101100000000000000000000000000 E
b11101100000000000000000000000000 L
b101 -
b101 H
b101 J
b110 .
b110 7
b110 I
b110 K
b11 B
1&
#1120000
0&
#1130000
1*
1,
1+
b11 A
b10 B
1&
#1140000
0&
#1150000
b111 1
b111 9
b111 F
b11 2
b11 5
b11 8
b10110000000000000000000000000000 0
b10110000000000000000000000000000 D
b10110000000000000000000000000000 M
0*
0,
0+
b10 A
b11 "
b11 3
b11 6
b11 G
b11011000000000000000000000000000 4
b11011000000000000000000000000000 :
b11011000000000000000000000000000 E
b11011000000000000000000000000000 L
b100 -
b100 H
b100 J
b101 .
b101 7
b101 I
b101 K
b11 B
1&
#1160000
0&
#1170000
1*
1,
1+
b11 A
b10 B
1&
#1180000
0&
#1190000
b10101 1
b10101 9
b10101 F
b1010 2
b1010 5
b1010 8
b1100000000000000000000000000000 0
b1100000000000000000000000000000 D
b1100000000000000000000000000000 M
0*
0,
0+
b10 A
b111 "
b111 3
b111 6
b111 G
b10110000000000000000000000000000 4
b10110000000000000000000000000000 :
b10110000000000000000000000000000 E
b10110000000000000000000000000000 L
b11 -
b11 H
b11 J
b100 .
b100 7
b100 I
b100 K
b11 B
1&
#1200000
0&
#1210000
1*
1,
1+
b11 A
b10 B
1&
#1220000
0&
#1230000
b11000 2
b11000 5
b11000 8
b11000000000000000000000000000000 0
b11000000000000000000000000000000 D
b11000000000000000000000000000000 M
b110000 1
b110000 9
b110000 F
0*
0,
0+
b10 A
b10101 "
b10101 3
b10101 6
b10101 G
b1100000000000000000000000000000 4
b1100000000000000000000000000000 :
b1100000000000000000000000000000 E
b1100000000000000000000000000000 L
b10 -
b10 H
b10 J
b11 .
b11 7
b11 I
b11 K
b11 B
1&
#1240000
0&
#1250000
1*
1,
1+
b11 A
b10 B
1&
#1260000
0&
#1270000
b110000 2
b110000 5
b110000 8
b10000000000000000000000000000000 0
b10000000000000000000000000000000 D
b10000000000000000000000000000000 M
b1100001 1
b1100001 9
b1100001 F
0*
0,
0+
b10 A
b110000 "
b110000 3
b110000 6
b110000 G
b11000000000000000000000000000000 4
b11000000000000000000000000000000 :
b11000000000000000000000000000000 E
b11000000000000000000000000000000 L
b1 -
b1 H
b1 J
b10 .
b10 7
b10 I
b10 K
b11 B
1&
#1280000
0&
#1290000
1*
1,
1+
b11 A
b10 B
1&
#1300000
0&
#1310000
b100100011 1
b100100011 9
b100100011 F
b10010001 2
b10010001 5
b10010001 8
b0 0
b0 D
b0 M
0*
0,
0+
b10 A
b1100001 "
b1100001 3
b1100001 6
b1100001 G
b10000000000000000000000000000000 4
b10000000000000000000000000000000 :
b10000000000000000000000000000000 E
b10000000000000000000000000000000 L
b0 -
b0 H
b0 J
b1 .
b1 7
b1 I
b1 K
b11 B
1&
#1320000
0&
#1330000
1*
1,
1+
b11 A
b10 B
1&
#1340000
0&
#1350000
b100100011 2
b100100011 5
b100100011 8
b1001000110 1
b1001000110 9
b1001000110 F
0*
0,
0+
b100 A
b100100011 "
b100100011 3
b100100011 6
b100100011 G
b0 4
b0 :
b0 E
b0 L
b111111 -
b111111 H
b111111 J
1/
b0 .
b0 7
b0 I
b0 K
b11 B
1&
#1360000
0&
#1370000
1!
b100 B
1&
#1380000
0&
#1390000
b1 @
1&
#1400000
0&
#1410000
b10 @
1&
